{
  "type": "asset",
  "_id": "89c41b8229d92ade",
  "folder": "18b30f608501bf56",
  "name": "Arauto do Trovão",
  "system": {
    "requirement": "<p>Se você empunha um poderoso martelo…</p>",
    "category": "Talento de Combate",
    "color": null,
    "fields": [],
    "abilities": [
      {
        "enabled": true,
        "description": "<p>Quando você @Compendium[foundry-ironsworn.ironswornmoves.c8bacc17f73d3103]{Enfrenta o Perigo}, @Compendium[foundry-ironsworn.ironswornmoves.4dd8468e095810a4]{Garante uma Vantagem} ou @Compendium[foundry-ironsworn.ironswornmoves.be95ca063ded2b19]{Compulsiona} golpeando ou quebrando um objeto inanimado, some +1 e receba +1 de momentum em um sucesso.</p>",
        "hasClock": false,
        "clockTicks": 0,
        "clockMax": 4
      },
      {
        "enabled": false,
        "description": "<p>Quando você @Compendium[foundry-ironsworn.ironswornmoves.5288e935906f6d28]{Golpeia} um inimigo para arremessá-lo para trás, atordoá-lo ou desequilibrá-lo, inflija 1 de dano (em vez de 2) e receba +2 de momentum em um sucesso. Em um sucesso decisivo, você também cria uma abertura e soma +1 em seu próximo movimento.</p>",
        "hasClock": false,
        "clockTicks": 0,
        "clockMax": 4
      },
      {
        "enabled": false,
        "description": "<p>Quando você @Compendium[foundry-ironsworn.ironswornmoves.12e23cfe23534a8f]{Muda o Destino}, pode @Compendium[foundry-ironsworn.ironswornmoves.5288e935906f6d28]{Golpear} com toda a fúria e poder que consegue reunir. Se fizer isso (decida antes de rolar), você pode rolar novamente quaisquer dados e infligir +2 de dano em um sucesso decisivo, mas conte um sucesso parcial como falha.</p>",
        "hasClock": false,
        "clockTicks": 0,
        "clockMax": 4
      }
    ],
    "track": {
      "enabled": false,
      "name": "Health",
      "current": 0,
      "max": 5,
      "value": 5,
      "min": 0
    },
    "exclusiveOptions": [],
    "conditions": [],
    "description": ""
  },
  "img": "icons/svg/item-bag.svg",
  "effects": [],
  "sort": 0,
  "ownership": {
    "default": 0
  },
  "flags": {
    "foundry-ironsworn": {
      "dfid": "Ironsworn/Assets/Combat_Talent/Thunder-Bringer",
      "dsid": "asset:classic/combat_talent/thunder_bringer"
    }
  },
  "_stats": {
    "systemId": "foundry-ironsworn"
  },
  "_key": "!items!89c41b8229d92ade"
}
